docs/source/conf.py
example/asynchronous_function.py
example/combining_stop_and_wait_conditions.py
example/customizing_retry_conditions_and_wait_conditions.py
example/http_example.py
example/synchronous_function.py
example/using_the_retry_context_manager.py
retry/__init__.py
retry/conditions.py
retry/retry.py
tests/__init__.py
tests/test_retry.py
retry_plus-1.0.5.dist-info/LICENSE
retry_plus-1.0.5.dist-info/METADATA
retry_plus-1.0.5.dist-info/WHEEL
retry_plus-1.0.5.dist-info/top_level.txt
retry_plus-1.0.5.dist-info/RECORD
