Metadata-Version: 2.1
Name: retry_plus
Version: 1.0.5
Summary: A generic retry package for Python
Home-page: https://github.com/talaatmagdyx/retry_plus
Author: Talaat Magdy
Author-email: Talaat Magdy <talaatmagdy75@gmail.com>
License: MIT License
Classifier: Programming Language :: Python :: 3
Classifier: License :: OSI Approved :: MIT License
Classifier: Operating System :: OS Independent
Requires-Python: >=3.6
License-File: LICENSE
Provides-Extra: dev
Requires-Dist: pytest ; extra == 'dev'
Requires-Dist: pytest-asyncio ; extra == 'dev'
Provides-Extra: docs
Requires-Dist: sphinx ; extra == 'docs'
Requires-Dist: myst-parser ; extra == 'docs'
Requires-Dist: readthedocs-sphinx-ext ; extra == 'docs'
Requires-Dist: sphinx-rtd-theme ; extra == 'docs'
